Aula02/pisca_leds.v
module pisca_leds(
	input clk_in1,
	output led_out1
);

reg [9:0]contador = 0;
reg l = 0;

assign led_out1 = l;

always @(posedge clk_in1) begin
	contador = contador + 1;
	if(contador == 0) begin
		l = ~l;
	end
end

endmodule

module testbench;
	
	wire led;
	reg clk = 0;
	
	pisca_leds Leds1(clk, led);
	
	always #2 clk = ~clk;

	initial begin
    $dumpvars;
    clk <= 0;
    #50000;
    $finish;
  end

endmodule

Aula02/dump.vcd
$date
	Thu Aug 17 17:37:26 2017
$end
$version
	Icarus Verilog
$end
$timescale
	1s
$end
$scope module testbench $end
$var wire 1 ! led $end
$var reg 1 " clk $end
$scope module Leds1 $end
$var wire 1 # clk_in1 $end
$var wire 1 ! led_out1 $end
$var reg 10 $ contador [9:0] $end
$var reg 1 % l $end
$upscope $end
$upscope $end
$enddefinitions $end
#0
$dumpvars
0%
b0 $
0#
0"
0!
$end
#2
b1 $
1"
1#
#4
0"
0#
#6
b10 $
1"
1#
#8
0"
0#
#10
b11 $
1"
1#
#12
0"
0#
#14
b100 $
1"
1#
#16
0"
0#
#18
b101 $
1"
1#
#20
0"
0#
#22
b110 $
1"
1#
#24
0"
0#
#26
b111 $
1"
1#
#28
0"
0#
#30
b1000 $
1"
1#
#32
0"
0#
#34
b1001 $
1"
1#
#36
0"
0#
#38
b1010 $
1"
1#
#40
0"
0#
#42
b1011 $
1"
1#
#44
0"
0#
#46
b1100 $
1"
1#
#48
0"
0#
#50
b1101 $
1"
1#
#52
0"
0#
#54
b1110 $
1"
1#
#56
0"
0#
#58
b1111 $
1"
1#
#60
0"
0#
#62
b10000 $
1"
1#
#64
0"
0#
#66
b10001 $
1"
1#
#68
0"
0#
#70
b10010 $
1"
1#
#72
0"
0#
#74
b10011 $
1"
1#
#76
0"
0#
#78
b10100 $
1"
1#
#80
0"
0#
#82
b10101 $
1"
1#
#84
0"
0#
#86
b10110 $
1"
1#
#88
0"
0#
#90
b10111 $
1"
1#
#92
0"
0#
#94
b11000 $
1"
1#
#96
0"
0#
#98
b11001 $
1"
1#
#100
0"
0#
#102
b11010 $
1"
1#
#104
0"
0#
#106
b11011 $
1"
1#
#108
0"
0#
#110
b11100 $
1"
1#
#112
0"
0#
#114
b11101 $
1"
1#
#116
0"
0#
#118
b11110 $
1"
1#
#120
0"
0#
#122
b11111 $
1"
1#
#124
0"
0#
#126
b100000 $
1"
1#
#128
0"
0#
#130
b100001 $
1"
1#
#132
0"
0#
#134
b100010 $
1"
1#
#136
0"
0#
#138
b100011 $
1"
1#
#140
0"
0#
#142
b100100 $
1"
1#
#144
0"
0#
#146
b100101 $
1"
1#
#148
0"
0#
#150
b100110 $
1"
1#
#152
0"
0#
#154
b100111 $
1"
1#
#156
0"
0#
#158
b101000 $
1"
1#
#160
0"
0#
#162
b101001 $
1"
1#
#164
0"
0#
#166
b101010 $
1"
1#
#168
0"
0#
#170
b101011 $
1"
1#
#172
0"
0#
#174
b101100 $
1"
1#
#176
0"
0#
#178
b101101 $
1"
1#
#180
0"
0#
#182
b101110 $
1"
1#
#184
0"
0#
#186
b101111 $
1"
1#
#188
0"
0#
#190
b110000 $
1"
1#
#192
0"
0#
#194
b110001 $
1"
1#
#196
0"
0#
#198
b110010 $
1"
1#
#200
0"
0#
#202
b110011 $
1"
1#
#204
0"
0#
#206
b110100 $
1"
1#
#208
0"
0#
#210
b110101 $
1"
1#
#212
0"
0#
#214
b110110 $
1"
1#
#216
0"
0#
#218
b110111 $
1"
1#
#220
0"
0#
#222
b111000 $
1"
1#
#224
0"
0#
#226
b111001 $
1"
1#
#228
0"
0#
#230
b111010 $
1"
1#
#232
0"
0#
#234
b111011 $
1"
1#
#236
0"
0#
#238
b111100 $
1"
1#
#240
0"
0#
#242
b111101 $
1"
1#
#244
0"
0#
#246
b111110 $
1"
1#
#248
0"
0#
#250
b111111 $
1"
1#
#252
0"
0#
#254
b1000000 $
1"
1#
#256
0"
0#
#258
b1000001 $
1"
1#
#260
0"
0#
#262
b1000010 $
1"
1#
#264
0"
0#
#266
b1000011 $
1"
1#
#268
0"
0#
#270
b1000100 $
1"
1#
#272
0"
0#
#274
b1000101 $
1"
1#
#276
0"
0#
#278
b1000110 $
1"
1#
#280
0"
0#
#282
b1000111 $
1"
1#
#284
0"
0#
#286
b1001000 $
1"
1#
#288
0"
0#
#290
b1001001 $
1"
1#
#292
0"
0#
#294
b1001010 $
1"
1#
#296
0"
0#
#298
b1001011 $
1"
1#
#300
0"
0#
#302
b1001100 $
1"
1#
#304
0"
0#
#306
b1001101 $
1"
1#
#308
0"
0#
#310
b1001110 $
1"
1#
#312
0"
0#
#314
b1001111 $
1"
1#
#316
0"
0#
#318
b1010000 $
1"
1#
#320
0"
0#
#322
b1010001 $
1"
1#
#324
0"
0#
#326
b1010010 $
1"
1#
#328
0"
0#
#330
b1010011 $
1"
1#
#332
0"
0#
#334
b1010100 $
1"
1#
#336
0"
0#
#338
b1010101 $
1"
1#
#340
0"
0#
#342
b1010110 $
1"
1#
#344
0"
0#
#346
b1010111 $
1"
1#
#348
0"
0#
#350
b1011000 $
1"
1#
#352
0"
0#
#354
b1011001 $
1"
1#
#356
0"
0#
#358
b1011010 $
1"
1#
#360
0"
0#
#362
b1011011 $
1"
1#
#364
0"
0#
#366
b1011100 $
1"
1#
#368
0"
0#
#370
b1011101 $
1"
1#
#372
0"
0#
#374
b1011110 $
1"
1#
#376
0"
0#
#378
b1011111 $
1"
1#
#380
0"
0#
#382
b1100000 $
1"
1#
#384
0"
0#
#386
b1100001 $
1"
1#
#388
0"
0#
#390
b1100010 $
1"
1#
#392
0"
0#
#394
b1100011 $
1"
1#
#396
0"
0#
#398
b1100100 $
1"
1#
#400
0"
0#
#402
b1100101 $
1"
1#
#404
0"
0#
#406
b1100110 $
1"
1#
#408
0"
0#
#410
b1100111 $
1"
1#
#412
0"
0#
#414
b1101000 $
1"
1#
#416
0"
0#
#418
b1101001 $
1"
1#
#420
0"
0#
#422
b1101010 $
1"
1#
#424
0"
0#
#426
b1101011 $
1"
1#
#428
0"
0#
#430
b1101100 $
1"
1#
#432
0"
0#
#434
b1101101 $
1"
1#
#436
0"
0#
#438
b1101110 $
1"
1#
#440
0"
0#
#442
b1101111 $
1"
1#
#444
0"
0#
#446
b1110000 $
1"
1#
#448
0"
0#
#450
b1110001 $
1"
1#
#452
0"
0#
#454
b1110010 $
1"
1#
#456
0"
0#
#458
b1110011 $
1"
1#
#460
0"
0#
#462
b1110100 $
1"
1#
#464
0"
0#
#466
b1110101 $
1"
1#
#468
0"
0#
#470
b1110110 $
1"
1#
#472
0"
0#
#474
b1110111 $
1"
1#
#476
0"
0#
#478
b1111000 $
1"
1#
#480
0"
0#
#482
b1111001 $
1"
1#
#484
0"
0#
#486
b1111010 $
1"
1#
#488
0"
0#
#490
b1111011 $
1"
1#
#492
0"
0#
#494
b1111100 $
1"
1#
#496
0"
0#
#498
b1111101 $
1"
1#
#500
0"
0#
#502
b1111110 $
1"
1#
#504
0"
0#
#506
b1111111 $
1"
1#
#508
0"
0#
#510
b10000000 $
1"
1#
#512
0"
0#
#514
b10000001 $
1"
1#
#516
0"
0#
#518
b10000010 $
1"
1#
#520
0"
0#
#522
b10000011 $
1"
1#
#524
0"
0#
#526
b10000100 $
1"
1#
#528
0"
0#
#530
b10000101 $
1"
1#
#532
0"
0#
#534
b10000110 $
1"
1#
#536
0"
0#
#538
b10000111 $
1"
1#
#540
0"
0#
#542
b10001000 $
1"
1#
#544
0"
0#
#546
b10001001 $
1"
1#
#548
0"
0#
#550
b10001010 $
1"
1#
#552
0"
0#
#554
b10001011 $
1"
1#
#556
0"
0#
#558
b10001100 $
1"
1#
#560
0"
0#
#562
b10001101 $
1"
1#
#564
0"
0#
#566
b10001110 $
1"
1#
#568
0"
0#
#570
b10001111 $
1"
1#
#572
0"
0#
#574
b10010000 $
1"
1#
#576
0"
0#
#578
b10010001 $
1"
1#
#580
0"
0#
#582
b10010010 $
1"
1#
#584
0"
0#
#586
b10010011 $
1"
1#
#588
0"
0#
#590
b10010100 $
1"
1#
#592
0"
0#
#594
b10010101 $
1"
1#
#596
0"
0#
#598
b10010110 $
1"
1#
#600
0"
0#
#602
b10010111 $
1"
1#
#604
0"
0#
#606
b10011000 $
1"
1#
#608
0"
0#
#610
b10011001 $
1"
1#
#612
0"
0#
#614
b10011010 $
1"
1#
#616
0"
0#
#618
b10011011 $
1"
1#
#620
0"
0#
#622
b10011100 $
1"
1#
#624
0"
0#
#626
b10011101 $
1"
1#
#628
0"
0#
#630
b10011110 $
1"
1#
#632
0"
0#
#634
b10011111 $
1"
1#
#636
0"
0#
#638
b10100000 $
1"
1#
#640
0"
0#
#642
b10100001 $
1"
1#
#644
0"
0#
#646
b10100010 $
1"
1#
#648
0"
0#
#650
b10100011 $
1"
1#
#652
0"
0#
#654
b10100100 $
1"
1#
#656
0"
0#
#658
b10100101 $
1"
1#
#660
0"
0#
#662
b10100110 $
1"
1#
#664
0"
0#
#666
b10100111 $
1"
1#
#668
0"
0#
#670
b10101000 $
1"
1#
#672
0"
0#
#674
b10101001 $
1"
1#
#676
0"
0#
#678
b10101010 $
1"
1#
#680
0"
0#
#682
b10101011 $
1"
1#
#684
0"
0#
#686
b10101100 $
1"
1#
#688
0"
0#
#690
b10101101 $
1"
1#
#692
0"
0#
#694
b10101110 $
1"
1#
#696
0"
0#
#698
b10101111 $
1"
1#
#700
0"
0#
#702
b10110000 $
1"
1#
#704
0"
0#
#706
b10110001 $
1"
1#
#708
0"
0#
#710
b10110010 $
1"
1#
#712
0"
0#
#714
b10110011 $
1"
1#
#716
0"
0#
#718
b10110100 $
1"
1#
#720
0"
0#
#722
b10110101 $
1"
1#
#724
0"
0#
#726
b10110110 $
1"
1#
#728
0"
0#
#730
b10110111 $
1"
1#
#732
0"
0#
#734
b10111000 $
1"
1#
#736
0"
0#
#738
b10111001 $
1"
1#
#740
0"
0#
#742
b10111010 $
1"
1#
#744
0"
0#
#746
b10111011 $
1"
1#
#748
0"
0#
#750
b10111100 $
1"
1#
#752
0"
0#
#754
b10111101 $
1"
1#
#756
0"
0#
#758
b10111110 $
1"
1#
#760
0"
0#
#762
b10111111 $
1"
1#
#764
0"
0#
#766
b11000000 $
1"
1#
#768
0"
0#
#770
b11000001 $
1"
1#
#772
0"
0#
#774
b11000010 $
1"
1#
#776
0"
0#
#778
b11000011 $
1"
1#
#780
0"
0#
#782
b11000100 $
1"
1#
#784
0"
0#
#786
b11000101 $
1"
1#
#788
0"
0#
#790
b11000110 $
1"
1#
#792
0"
0#
#794
b11000111 $
1"
1#
#796
0"
0#
#798
b11001000 $
1"
1#
#800
0"
0#
#802
b11001001 $
1"
1#
#804
0"
0#
#806
b11001010 $
1"
1#
#808
0"
0#
#810
b11001011 $
1"
1#
#812
0"
0#
#814
b11001100 $
1"
1#
#816
0"
0#
#818
b11001101 $
1"
1#
#820
0"
0#
#822
b11001110 $
1"
1#
#824
0"
0#
#826
b11001111 $
1"
1#
#828
0"
0#
#830
b11010000 $
1"
1#
#832
0"
0#
#834
b11010001 $
1"
1#
#836
0"
0#
#838
b11010010 $
1"
1#
#840
0"
0#
#842
b11010011 $
1"
1#
#844
0"
0#
#846
b11010100 $
1"
1#
#848
0"
0#
#850
b11010101 $
1"
1#
#852
0"
0#
#854
b11010110 $
1"
1#
#856
0"
0#
#858
b11010111 $
1"
1#
#860
0"
0#
#862
b11011000 $
1"
1#
#864
0"
0#
#866
b11011001 $
1"
1#
#868
0"
0#
#870
b11011010 $
1"
1#
#872
0"
0#
#874
b11011011 $
1"
1#
#876
0"
0#
#878
b11011100 $
1"
1#
#880
0"
0#
#882
b11011101 $
1"
1#
#884
0"
0#
#886
b11011110 $
1"
1#
#888
0"
0#
#890
b11011111 $
1"
1#
#892
0"
0#
#894
b11100000 $
1"
1#
#896
0"
0#
#898
b11100001 $
1"
1#
#900
0"
0#
#902
b11100010 $
1"
1#
#904
0"
0#
#906
b11100011 $
1"
1#
#908
0"
0#
#910
b11100100 $
1"
1#
#912
0"
0#
#914
b11100101 $
1"
1#
#916
0"
0#
#918
b11100110 $
1"
1#
#920
0"
0#
#922
b11100111 $
1"
1#
#924
0"
0#
#926
b11101000 $
1"
1#
#928
0"
0#
#930
b11101001 $
1"
1#
#932
0"
0#
#934
b11101010 $
1"
1#
#936
0"
0#
#938
b11101011 $
1"
1#
#940
0"
0#
#942
b11101100 $
1"
1#
#944
0"
0#
#946
b11101101 $
1"
1#
#948
0"
0#
#950
b11101110 $
1"
1#
#952
0"
0#
#954
b11101111 $
1"
1#
#956
0"
0#
#958
b11110000 $
1"
1#
#960
0"
0#
#962
b11110001 $
1"
1#
#964
0"
0#
#966
b11110010 $
1"
1#
#968
0"
0#
#970
b11110011 $
1"
1#
#972
0"
0#
#974
b11110100 $
1"
1#
#976
0"
0#
#978
b11110101 $
1"
1#
#980
0"
0#
#982
b11110110 $
1"
1#
#984
0"
0#
#986
b11110111 $
1"
1#
#988
0"
0#
#990
b11111000 $
1"
1#
#992
0"
0#
#994
b11111001 $
1"
1#
#996
0"
0#
#998
b11111010 $
1"
1#
#1000
0"
0#
#1002
b11111011 $
1"
1#
#1004
0"
0#
#1006
b11111100 $
1"
1#
#1008
0"
0#
#1010
b11111101 $
1"
1#
#1012
0"
0#
#1014
b11111110 $
1"
1#
#1016
0"
0#
#1018
b11111111 $
1"
1#
#1020
0"
0#
#1022
b100000000 $
1"
1#
#1024
0"
0#
#1026
b100000001 $
1"
1#
#1028
0"
0#
#1030
b100000010 $
1"
1#
#1032
0"
0#
#1034
b100000011 $
1"
1#
#1036
0"
0#
#1038
b100000100 $
1"
1#
#1040
0"
0#
#1042
b100000101 $
1"
1#
#1044
0"
0#
#1046
b100000110 $
1"
1#
#1048
0"
0#
#1050
b100000111 $
1"
1#
#1052
0"
0#
#1054
b100001000 $
1"
1#
#1056
0"
0#
#1058
b100001001 $
1"
1#
#1060
0"
0#
#1062
b100001010 $
1"
1#
#1064
0"
0#
#1066
b100001011 $
1"
1#
#1068
0"
0#
#1070
b100001100 $
1"
1#
#1072
0"
0#
#1074
b100001101 $
1"
1#
#1076
0"
0#
#1078
b100001110 $
1"
1#
#1080
0"
0#
#1082
b100001111 $
1"
1#
#1084
0"
0#
#1086
b100010000 $
1"
1#
#1088
0"
0#
#1090
b100010001 $
1"
1#
#1092
0"
0#
#1094
b100010010 $
1"
1#
#1096
0"
0#
#1098
b100010011 $
1"
1#
#1100
0"
0#
#1102
b100010100 $
1"
1#
#1104
0"
0#
#1106
b100010101 $
1"
1#
#1108
0"
0#
#1110
b100010110 $
1"
1#
#1112
0"
0#
#1114
b100010111 $
1"
1#
#1116
0"
0#
#1118
b100011000 $
1"
1#
#1120
0"
0#
#1122
b100011001 $
1"
1#
#1124
0"
0#
#1126
b100011010 $
1"
1#
#1128
0"
0#
#1130
b100011011 $
1"
1#
#1132
0"
0#
#1134
b100011100 $
1"
1#
#1136
0"
0#
#1138
b100011101 $
1"
1#
#1140
0"
0#
#1142
b100011110 $
1"
1#
#1144
0"
0#
#1146
b100011111 $
1"
1#
#1148
0"
0#
#1150
b100100000 $
1"
1#
#1152
0"
0#
#1154
b100100001 $
1"
1#
#1156
0"
0#
#1158
b100100010 $
1"
1#
#1160
0"
0#
#1162
b100100011 $
1"
1#
#1164
0"
0#
#1166
b100100100 $
1"
1#
#1168
0"
0#
#1170
b100100101 $
1"
1#
#1172
0"
0#
#1174
b100100110 $
1"
1#
#1176
0"
0#
#1178
b100100111 $
1"
1#
#1180
0"
0#
#1182
b100101000 $
1"
1#
#1184
0"
0#
#1186
b100101001 $
1"
1#
#1188
0"
0#
#1190
b100101010 $
1"
1#
#1192
0"
0#
#1194
b100101011 $
1"
1#
#1196
0"
0#
#1198
b100101100 $
1"
1#
#1200
0"
0#
#1202
b100101101 $
1"
1#
#1204
0"
0#
#1206
b100101110 $
1"
1#
#1208
0"
0#
#1210
b100101111 $
1"
1#
#1212
0"
0#
#1214
b100110000 $
1"
1#
#1216
0"
0#
#1218
b100110001 $
1"
1#
#1220
0"
0#
#1222
b100110010 $
1"
1#
#1224
0"
0#
#1226
b100110011 $
1"
1#
#1228
0"
0#
#1230
b100110100 $
1"
1#
#1232
0"
0#
#1234
b100110101 $
1"
1#
#1236
0"
0#
#1238
b100110110 $
1"
1#
#1240
0"
0#
#1242
b100110111 $
1"
1#
#1244
0"
0#
#1246
b100111000 $
1"
1#
#1248
0"
0#
#1250
b100111001 $
1"
1#
#1252
0"
0#
#1254
b100111010 $
1"
1#
#1256
0"
0#
#1258
b100111011 $
1"
1#
#1260
0"
0#
#1262
b100111100 $
1"
1#
#1264
0"
0#
#1266
b100111101 $
1"
1#
#1268
0"
0#
#1270
b100111110 $
1"
1#
#1272
0"
0#
#1274
b100111111 $
1"
1#
#1276
0"
0#
#1278
b101000000 $
1"
1#
#1280
0"
0#
#1282
b101000001 $
1"
1#
#1284
0"
0#
#1286
b101000010 $
1"
1#
#1288
0"
0#
#1290
b101000011 $
1"
1#
#1292
0"
0#
#1294
b101000100 $
1"
1#
#1296
0"
0#
#1298
b101000101 $
1"
1#
#1300
0"
0#
#1302
b101000110 $
1"
1#
#1304
0"
0#
#1306
b101000111 $
1"
1#
#1308
0"
0#
#1310
b101001000 $
1"
1#
#1312
0"
0#
#1314
b101001001 $
1"
1#
#1316
0"
0#
#1318
b101001010 $
1"
1#
#1320
0"
0#
#1322
b101001011 $
1"
1#
#1324
0"
0#
#1326
b101001100 $
1"
1#
#1328
0"
0#
#1330
b101001101 $
1"
1#
#1332
0"
0#
#1334
b101001110 $
1"
1#
#1336
0"
0#
#1338
b101001111 $
1"
1#
#1340
0"
0#
#1342
b101010000 $
1"
1#
#1344
0"
0#
#1346
b101010001 $
1"
1#
#1348
0"
0#
#1350
b101010010 $
1"
1#
#1352
0"
0#
#1354
b101010011 $
1"
1#
#1356
0"
0#
#1358
b101010100 $
1"
1#
#1360
0"
0#
#1362
b101010101 $
1"
1#
#1364
0"
0#
#1366
b101010110 $
1"
1#
#1368
0"
0#
#1370
b101010111 $
1"
1#
#1372
0"
0#
#1374
b101011000 $
1"
1#
#1376
0"
0#
#1378
b101011001 $
1"
1#
#1380
0"
0#
#1382
b101011010 $
1"
1#
#1384
0"
0#
#1386
b101011011 $
1"
1#
#1388
0"
0#
#1390
b101011100 $
1"
1#
#1392
0"
0#
#1394
b101011101 $
1"
1#
#1396
0"
0#
#1398
b101011110 $
1"
1#
#1400
0"
0#
#1402
b101011111 $
1"
1#
#1404
0"
0#
#1406
b101100000 $
1"
1#
#1408
0"
0#
#1410
b101100001 $
1"
1#
#1412
0"
0#
#1414
b101100010 $
1"
1#
#1416
0"
0#
#1418
b101100011 $
1"
1#
#1420
0"
0#
#1422
b101100100 $
1"
1#
#1424
0"
0#
#1426
b101100101 $
1"
1#
#1428
0"
0#
#1430
b101100110 $
1"
1#
#1432
0"
0#
#1434
b101100111 $
1"
1#
#1436
0"
0#
#1438
b101101000 $
1"
1#
#1440
0"
0#
#1442
b101101001 $
1"
1#
#1444
0"
0#
#1446
b101101010 $
1"
1#
#1448
0"
0#
#1450
b101101011 $
1"
1#
#1452
0"
0#
#1454
b101101100 $
1"
1#
#1456
0"
0#
#1458
b101101101 $
1"
1#
#1460
0"
0#
#1462
b101101110 $
1"
1#
#1464
0"
0#
#1466
b101101111 $
1"
1#
#1468
0"
0#
#1470
b101110000 $
1"
1#
#1472
0"
0#
#1474
b101110001 $
1"
1#
#1476
0"
0#
#1478
b101110010 $
1"
1#
#1480
0"
0#
#1482
b101110011 $
1"
1#
#1484
0"
0#
#1486
b101110100 $
1"
1#
#1488
0"
0#
#1490
b101110101 $
1"
1#
#1492
0"
0#
#1494
b101110110 $
1"
1#
#1496
0"
0#
#1498
b101110111 $
1"
1#
#1500
0"
0#
#1502
b101111000 $
1"
1#
#1504
0"
0#
#1506
b101111001 $
1"
1#
#1508
0"
0#
#1510
b101111010 $
1"
1#
#1512
0"
0#
#1514
b101111011 $
1"
1#
#1516
0"
0#
#1518
b101111100 $
1"
1#
#1520
0"
0#
#1522
b101111101 $
1"
1#
#1524
0"
0#
#1526
b101111110 $
1"
1#
#1528
0"
0#
#1530
b101111111 $
1"
1#
#1532
0"
0#
#1534
b110000000 $
1"
1#
#1536
0"
0#
#1538
b110000001 $
1"
1#
#1540
0"
0#
#1542
b110000010 $
1"
1#
#1544
0"
0#
#1546
b110000011 $
1"
1#
#1548
0"
0#
#1550
b110000100 $
1"
1#
#1552
0"
0#
#1554
b110000101 $
1"
1#
#1556
0"
0#
#1558
b110000110 $
1"
1#
#1560
0"
0#
#1562
b110000111 $
1"
1#
#1564
0"
0#
#1566
b110001000 $
1"
1#
#1568
0"
0#
#1570
b110001001 $
1"
1#
#1572
0"
0#
#1574
b110001010 $
1"
1#
#1576
0"
0#
#1578
b110001011 $
1"
1#
#1580
0"
0#
#1582
b110001100 $
1"
1#
#1584
0"
0#
#1586
b110001101 $
1"
1#
#1588
0"
0#
#1590
b110001110 $
1"
1#
#1592
0"
0#
#1594
b110001111 $
1"
1#
#1596
0"
0#
#1598
b110010000 $
1"
1#
#1600
0"
0#
#1602
b110010001 $
1"
1#
#1604
0"
0#
#1606
b110010010 $
1"
1#
#1608
0"
0#
#1610
b110010011 $
1"
1#
#1612
0"
0#
#1614
b110010100 $
1"
1#
#1616
0"
0#
#1618
b110010101 $
1"
1#
#1620
0"
0#
#1622
b110010110 $
1"
1#
#1624
0"
0#
#1626
b110010111 $
1"
1#
#1628
0"
0#
#1630
b110011000 $
1"
1#
#1632
0"
0#
#1634
b110011001 $
1"
1#
#1636
0"
0#
#1638
b110011010 $
1"
1#
#1640
0"
0#
#1642
b110011011 $
1"
1#
#1644
0"
0#
#1646
b110011100 $
1"
1#
#1648
0"
0#
#1650
b110011101 $
1"
1#
#1652
0"
0#
#1654
b110011110 $
1"
1#
#1656
0"
0#
#1658
b110011111 $
1"
1#
#1660
0"
0#
#1662
b110100000 $
1"
1#
#1664
0"
0#
#1666
b110100001 $
1"
1#
#1668
0"
0#
#1670
b110100010 $
1"
1#
#1672
0"
0#
#1674
b110100011 $
1"
1#
#1676
0"
0#
#1678
b110100100 $
1"
1#
#1680
0"
0#
#1682
b110100101 $
1"
1#
#1684
0"
0#
#1686
b110100110 $
1"
1#
#1688
0"
0#
#1690
b110100111 $
1"
1#
#1692
0"
0#
#1694
b110101000 $
1"
1#
#1696
0"
0#
#1698
b110101001 $
1"
1#
#1700
0"
0#
#1702
b110101010 $
1"
1#
#1704
0"
0#
#1706
b110101011 $
1"
1#
#1708
0"
0#
#1710
b110101100 $
1"
1#
#1712
0"
0#
#1714
b110101101 $
1"
1#
#1716
0"
0#
#1718
b110101110 $
1"
1#
#1720
0"
0#
#1722
b110101111 $
1"
1#
#1724
0"
0#
#1726
b110110000 $
1"
1#
#1728
0"
0#
#1730
b110110001 $
1"
1#
#1732
0"
0#
#1734
b110110010 $
1"
1#
#1736
0"
0#
#1738
b110110011 $
1"
1#
#1740
0"
0#
#1742
b110110100 $
1"
1#
#1744
0"
0#
#1746
b110110101 $
1"
1#
#1748
0"
0#
#1750
b110110110 $
1"
1#
#1752
0"
0#
#1754
b110110111 $
1"
1#
#1756
0"
0#
#1758
b110111000 $
1"
1#
#1760
0"
0#
#1762
b110111001 $
1"
1#
#1764
0"
0#
#1766
b110111010 $
1"
1#
#1768
0"
0#
#1770
b110111011 $
1"
1#
#1772
0"
0#
#1774
b110111100 $
1"
1#
#1776
0"
0#
#1778
b110111101 $
1"
1#
#1780
0"
0#
#1782
b110111110 $
1"
1#
#1784
0"
0#
#1786
b110111111 $
1"
1#
#1788
0"
0#
#1790
b111000000 $
1"
1#
#1792
0"
0#
#1794
b111000001 $
1"
1#
#1796
0"
0#
#1798
b111000010 $
1"
1#
#1800
0"
0#
#1802
b111000011 $
1"
1#
#1804
0"
0#
#1806
b111000100 $
1"
1#
#1808
0"
0#
#1810
b111000101 $
1"
1#
#1812
0"
0#
#1814
b111000110 $
1"
1#
#1816
0"
0#
#1818
b111000111 $
1"
1#
#1820
0"
0#
#1822
b111001000 $
1"
1#
#1824
0"
0#
#1826
b111001001 $
1"
1#
#1828
0"
0#
#1830
b111001010 $
1"
1#
#1832
0"
0#
#1834
b111001011 $
1"
1#
#1836
0"
0#
#1838
b111001100 $
1"
1#
#1840
0"
0#
#1842
b111001101 $
1"
1#
#1844
0"
0#
#1846
b111001110 $
1"
1#
#1848
0"
0#
#1850
b111001111 $
1"
1#
#1852
0"
0#
#1854
b111010000 $
1"
1#
#1856
0"
0#
#1858
b111010001 $
1"
1#
#1860
0"
0#
#1862
b111010010 $
1"
1#
#1864
0"
0#
#1866
b111010011 $
1"
1#
#1868
0"
0#
#1870
b111010100 $
1"
1#
#1872
0"
0#
#1874
b111010101 $
1"
1#
#1876
0"
0#
#1878
b111010110 $
1"
1#
#1880
0"
0#
#1882
b111010111 $
1"
1#
#1884
0"
0#
#1886
b111011000 $
1"
1#
#1888
0"
0#
#1890
b111011001 $
1"
1#
#1892
0"
0#
#1894
b111011010 $
1"
1#
#1896
0"
0#
#1898
b111011011 $
1"
1#
#1900
0"
0#
#1902
b111011100 $
1"
1#
#1904
0"
0#
#1906
b111011101 $
1"
1#
#1908
0"
0#
#1910
b111011110 $
1"
1#
#1912
0"
0#
#1914
b111011111 $
1"
1#
#1916
0"
0#
#1918
b111100000 $
1"
1#
#1920
0"
0#
#1922
b111100001 $
1"
1#
#1924
0"
0#
#1926
b111100010 $
1"
1#
#1928
0"
0#
#1930
b111100011 $
1"
1#
#1932
0"
0#
#1934
b111100100 $
1"
1#
#1936
0"
0#
#1938
b111100101 $
1"
1#
#1940
0"
0#
#1942
b111100110 $
1"
1#
#1944
0"
0#
#1946
b111100111 $
1"
1#
#1948
0"
0#
#1950
b111101000 $
1"
1#
#1952
0"
0#
#1954
b111101001 $
1"
1#
#1956
0"
0#
#1958
b111101010 $
1"
1#
#1960
0"
0#
#1962
b111101011 $
1"
1#
#1964
0"
0#
#1966
b111101100 $
1"
1#
#1968
0"
0#
#1970
b111101101 $
1"
1#
#1972
0"
0#
#1974
b111101110 $
1"
1#
#1976
0"
0#
#1978
b111101111 $
1"
1#
#1980
0"
0#
#1982
b111110000 $
1"
1#
#1984
0"
0#
#1986
b111110001 $
1"
1#
#1988
0"
0#
#1990
b111110010 $
1"
1#
#1992
0"
0#
#1994
b111110011 $
1"
1#
#1996
0"
0#
#1998
b111110100 $
1"
1#
#2000
0"
0#
#2002
b111110101 $
1"
1#
#2004
0"
0#
#2006
b111110110 $
1"
1#
#2008
0"
0#
#2010
b111110111 $
1"
1#
#2012
0"
0#
#2014
b111111000 $
1"
1#
#2016
0"
0#
#2018
b111111001 $
1"
1#
#2020
0"
0#
#2022
b111111010 $
1"
1#
#2024
0"
0#
#2026
b111111011 $
1"
1#
#2028
0"
0#
#2030
b111111100 $
1"
1#
#2032
0"
0#
#2034
b111111101 $
1"
1#
#2036
0"
0#
#2038
b111111110 $
1"
1#
#2040
0"
0#
#2042
b111111111 $
1"
1#
#2044
0"
0#
#2046
b1000000000 $
1"
1#
#2048
0"
0#
#2050
b1000000001 $
1"
1#
#2052
0"
0#
#2054
b1000000010 $
1"
1#
#2056
0"
0#
#2058
b1000000011 $
1"
1#
#2060
0"
0#
#2062
b1000000100 $
1"
1#
#2064
0"
0#
#2066
b1000000101 $
1"
1#
#2068
0"
0#
#2070
b1000000110 $
1"
1#
#2072
0"
0#
#2074
b1000000111 $
1"
1#
#2076
0"
0#
#2078
b1000001000 $
1"
1#
#2080
0"
0#
#2082
b1000001001 $
1"
1#
#2084
0"
0#
#2086
b1000001010 $
1"
1#
#2088
0"
0#
#2090
b1000001011 $
1"
1#
#2092
0"
0#
#2094
b1000001100 $
1"
1#
#2096
0"
0#
#2098
b1000001101 $
1"
1#
#2100
0"
0#
#2102
b1000001110 $
1"
1#
#2104
0"
0#
#2106
b1000001111 $
1"
1#
#2108
0"
0#
#2110
b1000010000 $
1"
1#
#2112
0"
0#
#2114
b1000010001 $
1"
1#
#2116
0"
0#
#2118
b1000010010 $
1"
1#
#2120
0"
0#
#2122
b1000010011 $
1"
1#
#2124
0"
0#
#2126
b1000010100 $
1"
1#
#2128
0"
0#
#2130
b1000010101 $
1"
1#
#2132
0"
0#
#2134
b1000010110 $
1"
1#
#2136
0"
0#
#2138
b1000010111 $
1"
1#
#2140
0"
0#
#2142
b1000011000 $
1"
1#
#2144
0"
0#
#2146
b1000011001 $
1"
1#
#2148
0"
0#
#2150
b1000011010 $
1"
1#
#2152
0"
0#
#2154
b1000011011 $
1"
1#
#2156
0"
0#
#2158
b1000011100 $
1"
1#
#2160
0"
0#
#2162
b1000011101 $
1"
1#
#2164
0"
0#
#2166
b1000011110 $
1"
1#
#2168
0"
0#
#2170
b1000011111 $
1"
1#
#2172
0"
0#
#2174
b1000100000 $
1"
1#
#2176
0"
0#
#2178
b1000100001 $
1"
1#
#2180
0"
0#
#2182
b1000100010 $
1"
1#
#2184
0"
0#
#2186
b1000100011 $
1"
1#
#2188
0"
0#
#2190
b1000100100 $
1"
1#
#2192
0"
0#
#2194
b1000100101 $
1"
1#
#2196
0"
0#
#2198
b1000100110 $
1"
1#
#2200
0"
0#
#2202
b1000100111 $
1"
1#
#2204
0"
0#
#2206
b1000101000 $
1"
1#
#2208
0"
0#
#2210
b1000101001 $
1"
1#
#2212
0"
0#
#2214
b1000101010 $
1"
1#
#2216
0"
0#
#2218
b1000101011 $
1"
1#
#2220
0"
0#
#2222
b1000101100 $
1"
1#
#2224
0"
0#
#2226
b1000101101 $
1"
1#
#2228
0"
0#
#2230
b1000101110 $
1"
1#
